Metadata-Version: 2.1
Name: reverse-module-sv
Version: 0.2
Summary: reverse package
Author: Sadegh Vejdan
Author-email: vejdan.sm@gmail.com
